django_sslserver2/__init__.py
django_sslserver2/management/__init__.py
django_sslserver2/management/commands/__init__.py
django_sslserver2/management/commands/runsslserver.py
django_sslserver2-0.1.4.dist-info/LICENSE
django_sslserver2-0.1.4.dist-info/METADATA
django_sslserver2-0.1.4.dist-info/WHEEL
django_sslserver2-0.1.4.dist-info/top_level.txt
django_sslserver2-0.1.4.dist-info/RECORD
