Metadata-Version: 2.1
Name: django-sslserver2
Version: 0.1.4
Summary: Django package to support both HTTP and HTTPS as runserver command
Home-page: https://github.com/EstebanBorai/django-sslserver2
Author: Esteban Borai
Author-email: estebanborai@gmail.com
License: MIT
Platform: UNKNOWN
Classifier: Environment :: Web Environment
Classifier: Framework :: Django
Classifier: License :: OSI Approved :: MIT License
Classifier: Operating System :: OS Independent
Classifier: Programming Language :: Python
Classifier: Programming Language :: Python :: 3.10
License-File: LICENSE
Requires-Dist: django (>=3)
